PyRP/RP.py
PyRP/RPxlsx.py
PyRP/_RP.py
PyRP/__init__.py
PyRP/tk/__init__.py
PyRP/tk/acc.py
PyRP/tk/print.py
PyRP/win/RPLog.py
PyRP/win/RPWidgets.py
PyRP/win/RPWin.py
PyRP/win/__init__.py
PyRP/win/about.txt
PyRP/win/help.txt
PyRP/win/rp.ico
PyRP-0.2.data/scripts/RPWin.pyw
PyRP-0.2.dist-info/DESCRIPTION.rst
PyRP-0.2.dist-info/METADATA
PyRP-0.2.dist-info/RECORD
PyRP-0.2.dist-info/WHEEL
PyRP-0.2.dist-info/metadata.json
PyRP-0.2.dist-info/top_level.txt
