Metadata-Version: 2.0
Name: PyRP
Version: 0.2
Summary: A package to calculate the ARPO family of tie-breaking methods.
Home-page: http://xtsunxet.usc.es/carlos/software/RP_en.html
Author: José Carlos Díaz Ramos
Author-email: josecarlos.diaz@usc.es
License: UNKNOWN
Keywords: ARPO,Recursive performance,tie-break
Platform: UNKNOWN
Classifier: Development Status :: 4 - Beta
Classifier: Intended Audience :: End Users/Desktop
Classifier: Intended Audience :: Science/Research
Classifier: Topic :: Scientific/Engineering :: Mathematics
Classifier: License :: OSI Approved :: MIT License
Classifier: Programming Language :: Python :: 3.4
